pymacsay.py
pymacsay-1.0.1.dist-info/LICENSE
pymacsay-1.0.1.dist-info/WHEEL
pymacsay-1.0.1.dist-info/METADATA
pymacsay-1.0.1.dist-info/RECORD
