Metadata-Version: 2.1
Name: pymacsay
Version: 1.0.1
Summary: pymacsay is a wrapper for the command-line tool `say` in macOS
Home-page: https://github.com/amkdg/pymacsay
Author: amkdg
Author-email: amkdg@protonmail.com
Classifier: License :: OSI Approved :: MIT License
